{
  "token": "AVP-BB0229C17A01",
  "proyecto": "I.E. N° 157 JOSE ABELARDO QUIÑONEZ GONZALES",
  "hoja": "IE 157 CAP FAP",
  "grupo": "Evaluación estructural preliminar de pabellones comprometidos",
  "item": "18",
  "id_actividad": "AVP-460AC4AD",
  "responsable": "TATI+BRENDA",
  "responsable_nombre": "Tatiana Yudith Puicán Chirinos, Brenda Milagros Huaman Guevara",
  "email": "consultor580@proinversion.gob.pe; consultor610@proinversion.gob.pe",
  "telefono": "",
  "actividad": "Aumentar demanda por 10 años (Geología, Arquitectura, Costos y Presupuestos)",
  "fecha_inicio": "09/06/2026",
  "fecha_programada": "03/07/2026",
  "proximas_acciones": ""
}